taskorbit/__init__.py
taskorbit/__meta__.py
taskorbit/enums.py
taskorbit/filter.py
taskorbit/models.py
taskorbit/timer.py
taskorbit/utils.py
taskorbit/brokers/__init__.py
taskorbit/brokers/nats/__init__.py
taskorbit/brokers/nats/client.py
taskorbit/brokers/nats/configuration.py
taskorbit/dispatching/__init__.py
taskorbit/dispatching/dispatcher.py
taskorbit/dispatching/handler.py
taskorbit/dispatching/queue.py
taskorbit/dispatching/router.py
taskorbit/middlewares/__init__.py
taskorbit/middlewares/manager.py
taskorbit/middlewares/middleware.py
taskorbit-0.1.6a0.dist-info/METADATA
taskorbit-0.1.6a0.dist-info/WHEEL
taskorbit-0.1.6a0.dist-info/licenses/LICENSE
taskorbit-0.1.6a0.dist-info/RECORD
