Metadata-Version: 2.1
Name: taskorbit
Version: 0.1.6a0
Summary: Asynchronous framework for managing asynchronous execution of independent tasks
Project-URL: Documentation, https://morington.github.io/taskorbit/
Project-URL: Repository, https://github.com/morington/taskorbit/
Project-URL: Telegram community, https://t.me/+0ih_O4_AkhlkMThi
Author-email: Adam Morington <morington.mail@gmail.com>
License-Expression: MIT
License-File: LICENSE
Keywords: asyncio,framework,message brokers,nats,queue,task-manager,wrapper
Classifier: Development Status :: 3 - Alpha
Classifier: Framework :: AsyncIO
Classifier: Intended Audience :: Developers
Classifier: Intended Audience :: System Administrators
Classifier: License :: OSI Approved :: MIT License
Classifier: Programming Language :: Python :: 3.10
Classifier: Programming Language :: Python :: 3.11
Classifier: Programming Language :: Python :: Implementation :: PyPy
Classifier: Topic :: Software Development :: Libraries :: Application Frameworks
Classifier: Topic :: Software Development :: Libraries :: Python Modules
Classifier: Topic :: System :: Distributed Computing
Classifier: Topic :: Utilities
Classifier: Typing :: Typed
Requires-Python: >=3.10
Requires-Dist: magic-filter<1.1,>=1.0.12
Requires-Dist: nats-py>=2.6.0
Requires-Dist: ormsgpack>=1.4.2
